{
  "meta": {
    "round": "round 0 \u00b7 drop 1",
    "stake_reserved_pct": 10,
    "auction_close_iso": "",
    "auction_close_label": "tbd \u00b7 announced with the round 1 drop",
    "state": "open",
    "about": "12 pieces by saapai p. (2015\u2013present). pencil, colored pencil, pen, watercolor, mixed media. tap any tile to offer $1 over the current bid via imessage. 10% of the total portfolio stake is reserved for art holders."
  },
  "pieces": [
    {
      "id": "rainbow-heron-2019",
      "title": "heron, in color",
      "medium": "colored pencil on paper",
      "date": "2019-07-14",
      "note": "most stylised of the set \u2014 the plumage is the study, the bird is the frame. panel priced it highest.",
      "image": "/art/rainbow-heron.jpg",
      "start_bid": 5,
      "current_bid": null,
      "bid_count": 0,
      "status": "open",
      "tags": [
        "color",
        "portrait \u00b7 animal"
      ],
      "locked_preview": ""
    },
    {
      "id": "eagle-2018",
      "title": "bald eagle, watching",
      "medium": "graphite on paper",
      "date": "2018-07-22",
      "note": "feather texture is the study, not the bird.",
      "image": "/art/eagle.jpg",
      "start_bid": 4,
      "current_bid": null,
      "bid_count": 0,
      "status": "open",
      "tags": [
        "portrait \u00b7 animal",
        "texture study"
      ],
      "locked_preview": ""
    },
    {
      "id": "tarantula-2019",
      "title": "tarantula, orange on black",
      "medium": "colored pencil on paper",
      "date": "2019-01-01",
      "note": "colored pencil at high contrast; the orange is saturated without going flat.",
      "image": "/art/tarantula-colored.jpg",
      "start_bid": 4,
      "current_bid": null,
      "bid_count": 0,
      "status": "open",
      "tags": [
        "color",
        "entomology"
      ],
      "locked_preview": ""
    },
    {
      "id": "eagle-closeup-2020",
      "title": "eagle, up close",
      "medium": "graphite on paper",
      "date": "2020-03-30",
      "note": "close-up portrait \u2014 the pupil catch and the radial feathers carry it.",
      "image": "/art/eagle-closeup.jpg",
      "start_bid": 3,
      "current_bid": null,
      "bid_count": 0,
      "status": "open",
      "tags": [
        "portrait \u00b7 animal",
        "close-up"
      ],
      "locked_preview": ""
    },
    {
      "id": "robber-fly-2019",
      "title": "robber fly, feeding",
      "medium": "graphite on paper",
      "date": "2019-08-08",
      "note": "insect study; the wing-membrane gradient holds the piece together.",
      "image": "/art/robber-fly.jpg",
      "start_bid": 3,
      "current_bid": null,
      "bid_count": 0,
      "status": "open",
      "tags": [
        "study",
        "entomology"
      ],
      "locked_preview": ""
    },
    {
      "id": "bearded-profile-2020",
      "title": "profile, man-bun",
      "medium": "graphite on paper",
      "date": "2020-03-21",
      "note": "profile study; beard tonal range is where the hand shows.",
      "image": "/art/bearded-profile.jpg",
      "start_bid": 3,
      "current_bid": null,
      "bid_count": 0,
      "status": "open",
      "tags": [
        "portrait \u00b7 figure"
      ],
      "locked_preview": ""
    },
    {
      "id": "zentangle-conch-2018",
      "title": "conch, tangled",
      "medium": "pen on paper",
      "date": "2018-07-17",
      "note": "zentangle \u2014 each ridge a different pattern. patient rather than flashy.",
      "image": "/art/zentangle-conch.jpg",
      "start_bid": 2,
      "current_bid": null,
      "bid_count": 0,
      "status": "open",
      "tags": [
        "pattern",
        "pen"
      ],
      "locked_preview": ""
    },
    {
      "id": "child-portrait-2017",
      "title": "small face, large eyes",
      "medium": "graphite on paper",
      "date": "2017-07-15",
      "note": "softer pressure, warmer register. reference was a photograph.",
      "image": "/art/child-portrait.jpg",
      "start_bid": 2,
      "current_bid": null,
      "bid_count": 0,
      "status": "open",
      "tags": [
        "portrait",
        "soft-shading"
      ],
      "locked_preview": ""
    },
    {
      "id": "scorpion-2017",
      "title": "scorpion, raised tail",
      "medium": "graphite on paper",
      "date": "2017-07-18",
      "note": "anatomical \u2014 leg-bristles are the detail. earliest graphite work in the drop.",
      "image": "/art/scorpion.jpg",
      "start_bid": 2,
      "current_bid": null,
      "bid_count": 0,
      "status": "open",
      "tags": [
        "study",
        "entomology"
      ],
      "locked_preview": ""
    },
    {
      "id": "watercolor-face-2026",
      "title": "a face, unfinished",
      "medium": "crayon + watercolor on paper",
      "date": "2026-04-18",
      "note": "confident line, partial color. the kind of imperfection the art portfolio is looking for.",
      "image": "/art/watercolor-face.jpg",
      "start_bid": 3,
      "current_bid": null,
      "bid_count": 0,
      "status": "open",
      "tags": [
        "watercolor",
        "portrait",
        "hand-drawn"
      ],
      "locked_preview": ""
    },
    {
      "id": "kraft-folio-back",
      "title": "kraft folio, back cover",
      "medium": "photograph \u00b7 archival",
      "date": "2026-04-22",
      "note": "the portfolio the drop travels in. the frame, not the content.",
      "image": "/art/kraft-folio.jpg",
      "start_bid": 1,
      "current_bid": null,
      "bid_count": 0,
      "status": "open",
      "tags": [
        "archival",
        "meta"
      ],
      "locked_preview": ""
    },
    {
      "id": "tupac-basketball-2026",
      "title": "tupac \u00b7 basketball, on canvas",
      "medium": "stencil + spray paint on canvas",
      "date": "2026-04-25",
      "note": "two canvases hung side by side \u00b7 placeholder copy \u00b7 edit before launch.",
      "image": "/art/tupac-basketball.jpg",
      "start_bid": 4,
      "current_bid": null,
      "bid_count": 0,
      "status": "open",
      "tags": [
        "mixed-media",
        "stencil",
        "spray-paint"
      ],
      "locked_preview": ""
    }
  ]
}